{
  "generator-jhipster": {
    "applicationType": "microservice",
    "gitHubOrganization": "domenicolar",
    "baseName": "jTestApplication",
    "packageName": "io.github.jhipster.application",
    "serverPort": 8081,
    "serviceDiscoveryType": "eureka",
    "authenticationType": "jwt",
    "uaaBaseName": "../uaa",
    "cacheProvider": "hazelcast",
    "enableHibernateCache": true,
    "websocket": false,
    "databaseType": "sql",
    "devDatabaseType": "h2Disk",
    "prodDatabaseType": "mysql",
    "searchEngine": false,
    "enableSwaggerCodegen": "true",
    "messageBroker": false,
    "buildTool": "maven",
    "enableSocialSignIn": false,
    "useSass": false,
    "clientPackageManager": "yarn",
    "testFrameworks": [
      "gatling"
    ],
    "enableTranslation": false,
    "nativeLanguage": "en",
    "languages": [
      "en"
    ],
    "clientFramework": "angularX",
    "jhipsterVersion": "4.13.3",
    "packageFolder": "io/github/jhipster/application",
    "jwtSecretKey": "5f0b6fcdc3a6419d0dc02401f95ea6d799b97d28",
    "jhiPrefix": "jhi",
    "skipClient": true,
    "skipUserManagement": true
  }
}